{
  "parent": "minecraft:recipes/root",
  "criteria": {
    "has_bricks": {
      "conditions": {
        "items": [
          {
            "items": [
              "chang_sheng_jue:blue_stone_fine_bricks"
            ]
          }
        ]
      },
      "trigger": "minecraft:inventory_changed"
    },
    "has_the_recipe": {
      "conditions": {
        "recipe": "minecraft:cyan_stone_bricks_shapeless"
      },
      "trigger": "minecraft:recipe_unlocked"
    }
  },
  "requirements": [
    [
      "has_bricks",
      "has_the_recipe"
    ]
  ],
  "rewards": {
    "recipes": [
      "minecraft:cyan_stone_bricks_shapeless"
    ]
  },
  "sends_telemetry_event": false
}